Workbook

Sheet Start
A1: Test cockpit · Lumen renewal kit
A2: Companion to the test guide. Example data from six fictional persona-twin sessions is filled in – overwrite it with your own.
B4: How to use
A5: 1 | B5: Sessions | C5: Plan each interview: persona, mode (twin or real), date, tasks. Set Status to Done when the session is logged.
A6: 2 | B6: Task Log | C6: One row per task per session: result, time on task, ease (1–7), prompt needed, a quote.
A7: 3 | B7: Observations | C7: One row per session: the A1–A6 fields from the test guide and the four debrief ratings.
A8: 4 | B8: Assumptions | C8: Thresholds per assumption (set before testing). Result, n and Status calculate automatically.
A9: 5 | B9: Report | C9: The end result: scoreboard, task success, missing items, voices and next steps. Updates as you log.
B11: Legend
C12: Amber cells: enter or overwrite values here. All other cells calculate – don't type over them.
B13: Y / N / NA | C13: NA = task not run in this session. NA answers are left out of the shares, so always read n on the Assumptions sheet.
B14: Scales | C14: Ease 1 = very hard … 7 = very easy · Trust, usefulness, intent, preference 1 = not at all … 5 = fully
B16: Screens
B17: S1 | C17: Email (PDF p. 1)
B18: S2 | C18: Renewal kit page (p. 2–3)
B19: S3 | C19: Board slide (p. 4)
B20: S4 | C20: Method sheet (p. 5)
B21: S5 | C21: Forward dialog (p. 6)

Sheet Report
A1: Test report · Lumen renewal kit · Round 1
A2: EXAMPLE – fictional results from six persona-twin sessions, 9 Nov 2026. All figures update from the Task Log and Observations sheets.
B4: Sessions done | C4: Tasks run | D4: Task success | F4: Avg. ease (1–7) | G4: Usefulness (1–5) | H4: Confirmed | I4: Mixed | J4: Rejected
B5: =COUNTIF(Sessions!$K$5:$K$16,"Done") -> 6 | C5: =COUNTA('Task Log'!$C$5:$C$64) -> 16 | D5: =IFERROR(COUNTIF('Task Log'!$E$5:$E$64,"Success")/COUNTA('Task Log'!$E$5:$E$64),"") -> 0.8125 | F5: =IFERROR(AVERAGE('Task Log'!$G$5:$G$64),"") -> 5.25 | G5: =IFERROR(AVERAGE(Observations!$L$5:$L$16),"") -> 4 | H5: =COUNTIF(Assumptions!$I$5:$I$10,"Confirmed") -> 2 | I5: =COUNTIF(Assumptions!$I$5:$I$10,"Mixed") -> 3 | J5: =COUNTIF(Assumptions!$I$5:$I$10,"Rejected") -> 1
A7: Assumption scoreboard
A8: ID | B8: Assumption | C8: Result | D8: Target | E8: n | F8: Status | G8: What we learned
A9: =Assumptions!A5 -> A1 | B9: =Assumptions!B5 -> Librarians forward the kit as it is | C9: =Assumptions!G5 -> 0.66666667 | D9: ="≥ "&TEXT(Assumptions!E5,"0%") -> ≥ 67% | E9: =Assumptions!H5 -> 6 | F9: =Assumptions!I5 -> Confirmed | G9: =Assumptions!J5 -> Four of six would forward it unchanged. Miriam needs to add the board meeting date; Ulrike needs comparable figures.
A10: =Assumptions!A6 -> A2 | B10: =Assumptions!B6 -> Push beats login: people act on the email | C10: =Assumptions!G6 -> 0.66666667 | D10: ="≥ "&TEXT(Assumptions!E6,"0%") -> ≥ 83% | E10: =Assumptions!H6 -> 3 | F10: =Assumptions!I6 -> Mixed | G10: =Assumptions!J6 -> Two of three acted at once. Ana read it as marketing – the sender and subject need to say 'your library'.
A11: =Assumptions!A7 -> A3 | B11: =Assumptions!B7 -> A disclosed method makes publisher figures credible | C11: =Assumptions!G7 -> 3.8333333 | D11: ="≥ "&TEXT(Assumptions!E7,"0.0") -> ≥ 4.0 | E11: =Assumptions!H7 -> 6 | F11: =Assumptions!I7 -> Mixed | G11: =Assumptions!J7 -> Librarians trust it (4–5); the VP and the consortium stay at 3 and ask for an independent check.
A12: =Assumptions!A8 -> A4 | B12: =Assumptions!B8 -> Cost and compliance tip the decision, not impact | C12: =Assumptions!G8 -> 0.66666667 | D12: ="≥ "&TEXT(Assumptions!E8,"0%") -> ≥ 67% | E12: =Assumptions!H8 -> 6 | F12: =Assumptions!I8 -> Confirmed | G12: =Assumptions!J8 -> Cost and compliance win four of six. People wins with the VP and the researcher – keep the tile.
A13: =Assumptions!A9 -> A5 | B13: =Assumptions!B9 -> The kit is complete without manual additions | C13: =Assumptions!G9 -> 0.33333333 | D13: ="≥ "&TEXT(Assumptions!E9,"0%") -> ≥ 67% | E13: =Assumptions!H9 -> 6 | F13: =Assumptions!I9 -> Rejected | G13: =Assumptions!J9 -> Only two of six need nothing added: meeting date, SNSF, comparison with other publishers and peer benchmarks are missing.
A14: =Assumptions!A10 -> A6 | B14: =Assumptions!B10 -> The kit sparks interest in expanding | C14: =Assumptions!G10 -> 0.4 | D14: ="≥ "&TEXT(Assumptions!E10,"0%") -> ≥ 50% | E14: =Assumptions!H10 -> 5 | F14: =Assumptions!I10 -> Mixed | G14: =Assumptions!J10 -> Interest comes from the budget side (Miriam, Rainer); the VP and the consortium do not react to the scenario.
A16: Tasks
A17: Task | B17: Name | C17: Runs | D17: Success | E17: Help | F17: Failed | G17: Success rate | H17: Avg. time (s) | I17: Avg. ease
A18: =Lists!A5 -> T1 | B18: =Lists!B5 -> Receive the kit | C18: =COUNTIF('Task Log'!$C$5:$C$64,A18) -> 3 | D18: =COUNTIFS('Task Log'!$C$5:$C$64,A18,'Task Log'!$E$5:$E$64,"Success") -> 3 | E18: =COUNTIFS('Task Log'!$C$5:$C$64,A18,'Task Log'!$E$5:$E$64,"With help") -> 0 | F18: =COUNTIFS('Task Log'!$C$5:$C$64,A18,'Task Log'!$E$5:$E$64,"Failed") -> 0 | G18: =IFERROR(D18/C18,0) -> 1 | H18: =IFERROR(AVERAGEIFS('Task Log'!$F$5:$F$64,'Task Log'!$C$5:$C$64,A18),0) -> 45 | I18: =IFERROR(AVERAGEIFS('Task Log'!$G$5:$G$64,'Task Log'!$C$5:$C$64,A18),0) -> 6
A19: =Lists!A6 -> T2 | B19: =Lists!B6 -> Check a figure | C19: =COUNTIF('Task Log'!$C$5:$C$64,A19) -> 5 | D19: =COUNTIFS('Task Log'!$C$5:$C$64,A19,'Task Log'!$E$5:$E$64,"Success") -> 4 | E19: =COUNTIFS('Task Log'!$C$5:$C$64,A19,'Task Log'!$E$5:$E$64,"With help") -> 1 | F19: =COUNTIFS('Task Log'!$C$5:$C$64,A19,'Task Log'!$E$5:$E$64,"Failed") -> 0 | G19: =IFERROR(D19/C19,0) -> 0.8 | H19: =IFERROR(AVERAGEIFS('Task Log'!$F$5:$F$64,'Task Log'!$C$5:$C$64,A19),0) -> 94 | I19: =IFERROR(AVERAGEIFS('Task Log'!$G$5:$G$64,'Task Log'!$C$5:$C$64,A19),0) -> 5
A20: =Lists!A7 -> T3 | B20: =Lists!B7 -> Pass it on | C20: =COUNTIF('Task Log'!$C$5:$C$64,A20) -> 2 | D20: =COUNTIFS('Task Log'!$C$5:$C$64,A20,'Task Log'!$E$5:$E$64,"Success") -> 1 | E20: =COUNTIFS('Task Log'!$C$5:$C$64,A20,'Task Log'!$E$5:$E$64,"With help") -> 1 | F20: =COUNTIFS('Task Log'!$C$5:$C$64,A20,'Task Log'!$E$5:$E$64,"Failed") -> 0 | G20: =IFERROR(D20/C20,0) -> 0.5 | H20: =IFERROR(AVERAGEIFS('Task Log'!$F$5:$F$64,'Task Log'!$C$5:$C$64,A20),0) -> 110 | I20: =IFERROR(AVERAGEIFS('Task Log'!$G$5:$G$64,'Task Log'!$C$5:$C$64,A20),0) -> 5
A21: =Lists!A8 -> T4 | B21: =Lists!B8 -> Make the case | C21: =COUNTIF('Task Log'!$C$5:$C$64,A21) -> 4 | D21: =COUNTIFS('Task Log'!$C$5:$C$64,A21,'Task Log'!$E$5:$E$64,"Success") -> 3 | E21: =COUNTIFS('Task Log'!$C$5:$C$64,A21,'Task Log'!$E$5:$E$64,"With help") -> 1 | F21: =COUNTIFS('Task Log'!$C$5:$C$64,A21,'Task Log'!$E$5:$E$64,"Failed") -> 0 | G21: =IFERROR(D21/C21,0) -> 0.75 | H21: =IFERROR(AVERAGEIFS('Task Log'!$F$5:$F$64,'Task Log'!$C$5:$C$64,A21),0) -> 37.5 | I21: =IFERROR(AVERAGEIFS('Task Log'!$G$5:$G$64,'Task Log'!$C$5:$C$64,A21),0) -> 5.25
A22: =Lists!A9 -> T5 | B22: =Lists!B9 -> Plan ahead | C22: =COUNTIF('Task Log'!$C$5:$C$64,A22) -> 2 | D22: =COUNTIFS('Task Log'!$C$5:$C$64,A22,'Task Log'!$E$5:$E$64,"Success") -> 2 | E22: =COUNTIFS('Task Log'!$C$5:$C$64,A22,'Task Log'!$E$5:$E$64,"With help") -> 0 | F22: =COUNTIFS('Task Log'!$C$5:$C$64,A22,'Task Log'!$E$5:$E$64,"Failed") -> 0 | G22: =IFERROR(D22/C22,0) -> 1 | H22: =IFERROR(AVERAGEIFS('Task Log'!$F$5:$F$64,'Task Log'!$C$5:$C$64,A22),0) -> 57.5 | I22: =IFERROR(AVERAGEIFS('Task Log'!$G$5:$G$64,'Task Log'!$C$5:$C$64,A22),0) -> 5
A23: Rule: two or more failures on one task = usability fix, whatever the assumption status.
A39: Must-have items participants would add by hand
A40: =Observations!B5 -> P1 Dr. Miriam Kessler | C40: =IF(Observations!A5="","",IF(Observations!H5="N","Nothing missing",Observations!I5)) -> Board meeting date ([YOUR DATE] placeholder)
A41: =Observations!B6 -> P3 Dr. Rainer Hollmann | C41: =IF(Observations!A6="","",IF(Observations!H6="N","Nothing missing",Observations!I6)) -> Comparison with other publishers
A42: =Observations!B7 -> P4 Prof. Dr. Sabine Aigner | C42: =IF(Observations!A7="","",IF(Observations!H7="N","Nothing missing",Observations!I7)) -> Nothing missing
A43: =Observations!B8 -> P6 Dr. Ana Ferreira | C43: =IF(Observations!A8="","",IF(Observations!H8="N","Nothing missing",Observations!I8)) -> Nothing missing
A44: =Observations!B9 -> P2 Jonas Brändli | C44: =IF(Observations!A9="","",IF(Observations!H9="N","Nothing missing",Observations!I9)) -> SNSF compliance in the funder figure
A45: =Observations!B10 -> P5 Ulrike Sandmann | C45: =IF(Observations!A10="","",IF(Observations!H10="N","Nothing missing",Observations!I10)) -> Peer benchmark, standard monitoring fields
A47: Voices
A48: =Observations!B5 -> P1 Dr. Miriam Kessler | C48: =Observations!O5 -> "This saves me two days – if I can add the meeting date."
A49: =Observations!B6 -> P3 Dr. Rainer Hollmann | C49: =Observations!O6 -> "One page is right. I'd still want to know how other publishers compare."
A50: =Observations!B7 -> P4 Prof. Dr. Sabine Aigner | C50: =Observations!O7 -> "I'd sign this – but I'd ask who checked the numbers."
A51: =Observations!B8 -> P6 Dr. Ana Ferreira | C51: =Observations!O8 -> "Seeing my editing work on a board slide is a first."
A52: =Observations!B9 -> P2 Jonas Brändli | C52: =Observations!O9 -> "Without SNSF I'd still have to build my own table."
A53: =Observations!B10 -> P5 Ulrike Sandmann | C53: =Observations!O10 -> "Good for one university. For 14 I need the same figures from every publisher."
A55: Next iteration (example)
A56: 1. A5 Rejected → add an editable board meeting date to the kit and replace [YOUR DATE]; add SNSF to the funder figure for Swiss partners.
A57: 2. A3 Mixed → name an independent check on the method sheet (e.g. the consortium's own monitoring) and re-test with P4 and P5.
A58: 3. A2 Mixed → change sender and subject to read as a message to the library, not marketing; re-test with P6.
A59: 4. A6 Mixed → show the 2027 scenario only to budget holders; test the kit's forward to the director with P3.
A60: 5. Out of scope but recurring: comparison with other publishers (P3, P5) – decide with the Decider whether to open it up.

Sheet Assumptions
A1: Assumptions
A2: Six assumptions behind the renewal kit. Thresholds (amber) are inputs; Result, n and Status calculate from Observations.
A4: ID | B4: Assumption | C4: Sprint question | D4: Metric | E4: Confirmed at | F4: Rejected below | G4: Result | H4: n | I4: Status | J4: What we learned (example)
A5: A1 | B5: Librarians forward the kit as it is | C5: SQ1 | D5: Share who would forward or accept the slide unchanged | E5: 0.666 | F5: 0.5 | G5: =IFERROR(COUNTIF(Observations!$C$5:$C$16,"Y")/(COUNTIF(Observations!$C$5:$C$16,"Y")+COUNTIF(Observations!$C$5:$C$16,"N")),"") -> 0.66666667 | H5: =COUNTIF(Observations!$C$5:$C$16,"Y")+COUNTIF(Observations!$C$5:$C$16,"N") -> 6 | I5: =IF(OR(H5=0,G5=""),"No data",IF(G5>=E5,"Confirmed",IF(G5<F5,"Rejected","Mixed"))) -> Confirmed | J5: Four of six would forward it unchanged. Miriam needs to add the board meeting date; Ulrike needs comparable figures.
A6: A2 | B6: Push beats login: people act on the email | C6: SQ1 | D6: Share who act on the email (S1) without a prompt (sessions with T1) | E6: 0.833 | F6: 0.666 | G6: =IFERROR(COUNTIF(Observations!$D$5:$D$16,"Y")/(COUNTIF(Observations!$D$5:$D$16,"Y")+COUNTIF(Observations!$D$5:$D$16,"N")),"") -> 0.66666667 | H6: =COUNTIF(Observations!$D$5:$D$16,"Y")+COUNTIF(Observations!$D$5:$D$16,"N") -> 3 | I6: =IF(OR(H6=0,G6=""),"No data",IF(G6>=E6,"Confirmed",IF(G6<F6,"Rejected","Mixed"))) -> Mixed | J6: Two of three acted at once. Ana read it as marketing – the sender and subject need to say 'your library'.
A7: A3 | B7: A disclosed method makes publisher figures credible | C7: SQ2 | D7: Average trust rating after seeing the method (1–5) | E7: 4 | F7: 3.5 | G7: =IFERROR(AVERAGE(Observations!$E$5:$E$16),"") -> 3.8333333 | H7: =COUNT(Observations!$E$5:$E$16) -> 6 | I7: =IF(OR(H7=0,G7=""),"No data",IF(G7>=E7,"Confirmed",IF(G7<F7,"Rejected","Mixed"))) -> Mixed | J7: Librarians trust it (4–5); the VP and the consortium stay at 3 and ask for an independent check.
A8: A4 | B8: Cost and compliance tip the decision, not impact | C8: SQ3 | D8: Share naming Cost or Compliance as the most persuasive tile | E8: 0.666 | F8: 0.5 | G8: =IFERROR((COUNTIF(Observations!$G$5:$G$16,"Cost")+COUNTIF(Observations!$G$5:$G$16,"Compliance"))/COUNTIF(Observations!$G$5:$G$16,"?*"),"") -> 0.66666667 | H8: =COUNTIF(Observations!$G$5:$G$16,"?*") -> 6 | I8: =IF(OR(H8=0,G8=""),"No data",IF(G8>=E8,"Confirmed",IF(G8<F8,"Rejected","Mixed"))) -> Confirmed | J8: Cost and compliance win four of six. People wins with the VP and the researcher – keep the tile.
A9: A5 | B9: The kit is complete without manual additions | C9: SQ4 | D9: Share with no must-have item missing | E9: 0.666 | F9: 0.5 | G9: =IFERROR(COUNTIF(Observations!$H$5:$H$16,"N")/(COUNTIF(Observations!$H$5:$H$16,"Y")+COUNTIF(Observations!$H$5:$H$16,"N")),"") -> 0.33333333 | H9: =COUNTIF(Observations!$H$5:$H$16,"Y")+COUNTIF(Observations!$H$5:$H$16,"N") -> 6 | I9: =IF(OR(H9=0,G9=""),"No data",IF(G9>=E9,"Confirmed",IF(G9<F9,"Rejected","Mixed"))) -> Rejected | J9: Only two of six need nothing added: meeting date, SNSF, comparison with other publishers and peer benchmarks are missing.
A10: A6 | B10: The kit sparks interest in expanding | C10: SQ5 | D10: Share who ask about or act on the 2027 prepayment scenario | E10: 0.5 | F10: 0.333 | G10: =IFERROR(COUNTIF(Observations!$J$5:$J$16,"Y")/(COUNTIF(Observations!$J$5:$J$16,"Y")+COUNTIF(Observations!$J$5:$J$16,"N")),"") -> 0.4 | H10: =COUNTIF(Observations!$J$5:$J$16,"Y")+COUNTIF(Observations!$J$5:$J$16,"N") -> 5 | I10: =IF(OR(H10=0,G10=""),"No data",IF(G10>=E10,"Confirmed",IF(G10<F10,"Rejected","Mixed"))) -> Mixed | J10: Interest comes from the budget side (Miriam, Rainer); the VP and the consortium do not react to the scenario.
A12: Status rule: Confirmed if Result ≥ Confirmed at · Rejected if Result < Rejected below · Mixed in between. Shares count Y and N answers only; NA is left out, so check n.

Sheet Sessions
A1: Sessions
A2: One row per interview. Amber cells are inputs. Rows S01–S06 hold example data from six twin sessions.
A4: Session | B4: Order | C4: Persona | D4: Name | E4: Role | F4: Mode | G4: Date | H4: Tasks | I4: Interviewer | J4: Consent | K4: Status
A5: S01 | B5: 1 | C5: P1 | D5: Dr. Miriam Kessler | E5: OA Coordinator, University of Rheinfeld | F5: Twin | G5: 46335 | H5: T1, T2, T3, T5 | I5: Alexander Boll | J5: Y | K5: Done
A6: S02 | B6: 2 | C6: P3 | D6: Dr. Rainer Hollmann | E6: Library Director, University of Rheinfeld | F6: Twin | G6: 46335 | H6: T2, T4, T5 | I6: Alexander Boll | J6: Y | K6: Done
A7: S03 | B7: 3 | C7: P4 | D7: Prof. Dr. Sabine Aigner | E7: VP Research, University of Rheinfeld | F7: Twin | G7: 46335 | H7: T4, T2 | I7: Alexander Boll | J7: Y | K7: Done
A8: S04 | B8: 4 | C8: P6 | D8: Dr. Ana Ferreira | E8: Group Leader & guest editor, Rheinfeld | F8: Twin | G8: 46335 | H8: T1, T4 | I8: Alexander Boll | J8: Y | K8: Done
A9: S05 | B9: 5 | C9: P2 | D9: Jonas Brändli | E9: Data Steward, Aaretal UAS (CH) | F9: Twin | G9: 46335 | H9: T1, T2, T3 | I9: Alexander Boll | J9: Y | K9: Done
A10: S06 | B10: 6 | C10: P5 | D10: Ulrike Sandmann | E10: Head of Licensing, consortium of 14 | F10: Twin | G10: 46335 | H10: T2, T4 | I10: Alexander Boll | J10: Y | K10: Done
A11: S07 | B11: 7 | C11: R1 | D11: [real librarian 1] | E11: Validation interview | F11: Real | H11: T1, T2, T3 | I11: Alexander Boll | K11: Planned
A12: S08 | B12: 8 | C12: R2 | D12: [real librarian 2] | E12: Validation interview | F12: Real | H12: T1, T2, T3 | I12: Alexander Boll | K12: Planned
A13: S09 | B13: 9 | C13: R3 | D13: [real director] | E13: Validation interview | F13: Real | H13: T2, T4, T5 | I13: Alexander Boll | K13: Planned
A14: S10
A15: S11
A16: S12

Sheet Task Log
A1: Task Log
A2: One row per task per session. Enter Session, Task and the amber fields; Persona and Screens fill in.
A4: Session | B4: Persona | C4: Task | D4: Screens | E4: Result | F4: Time (s) | G4: Ease (1–7) | H4: Prompted | I4: Observation / quote
A5: S01 | B5: =IF(A5="","",IFERROR(INDEX(Sessions!$C$5:$C$16,MATCH(A5,Sessions!$A$5:$A$16,0))&" "&INDEX(Sessions!$D$5:$D$16,MATCH(A5,Sessions!$A$5:$A$16,0)),"")) -> P1 Dr. Miriam Kessler | C5: T1 | D5: =IF(C5="","",IFERROR(INDEX(Lists!$C$5:$C$9,MATCH(C5,Lists!$A$5:$A$9,0)),"")) -> S1 → S2 | E5: Success | F5: 45 | G5: 6 | H5: N | I5: Read EUR 51,060 first, then 93%. Opened the kit straight away: "Finally something I don't have to build."
A6: S01 | B6: =IF(A6="","",IFERROR(INDEX(Sessions!$C$5:$C$16,MATCH(A6,Sessions!$A$5:$A$16,0))&" "&INDEX(Sessions!$D$5:$D$16,MATCH(A6,Sessions!$A$5:$A$16,0)),"")) -> P1 Dr. Miriam Kessler | C6: T2 | D6: =IF(C6="","",IFERROR(INDEX(Lists!$C$5:$C$9,MATCH(C6,Lists!$A$5:$A$9,0)),"")) -> S2 → S4 | E6: Success | F6: 80 | G6: 6 | H6: N | I6: Found Check this figure under Cost; read the formula aloud.
A7: S01 | B7: =IF(A7="","",IFERROR(INDEX(Sessions!$C$5:$C$16,MATCH(A7,Sessions!$A$5:$A$16,0))&" "&INDEX(Sessions!$D$5:$D$16,MATCH(A7,Sessions!$A$5:$A$16,0)),"")) -> P1 Dr. Miriam Kessler | C7: T3 | D7: =IF(C7="","",IFERROR(INDEX(Lists!$C$5:$C$9,MATCH(C7,Lists!$A$5:$A$9,0)),"")) -> S3 → S5 | E7: With help | F7: 150 | G7: 4 | H7: Y | I7: Looked for a place to enter the board meeting date; [YOUR DATE] on S2 confused her.
A8: S01 | B8: =IF(A8="","",IFERROR(INDEX(Sessions!$C$5:$C$16,MATCH(A8,Sessions!$A$5:$A$16,0))&" "&INDEX(Sessions!$D$5:$D$16,MATCH(A8,Sessions!$A$5:$A$16,0)),"")) -> P1 Dr. Miriam Kessler | C8: T5 | D8: =IF(C8="","",IFERROR(INDEX(Lists!$C$5:$C$9,MATCH(C8,Lists!$A$5:$A$9,0)),"")) -> S2 | E8: Success | F8: 60 | G8: 5 | H8: N | I8: "Topping up early would help me – but Hollmann decides that."
A9: S02 | B9: =IF(A9="","",IFERROR(INDEX(Sessions!$C$5:$C$16,MATCH(A9,Sessions!$A$5:$A$16,0))&" "&INDEX(Sessions!$D$5:$D$16,MATCH(A9,Sessions!$A$5:$A$16,0)),"")) -> P3 Dr. Rainer Hollmann | C9: T2 | D9: =IF(C9="","",IFERROR(INDEX(Lists!$C$5:$C$9,MATCH(C9,Lists!$A$5:$A$9,0)),"")) -> S2 → S4 | E9: Success | F9: 70 | G9: 6 | H9: N | I9: Went to the method sheet unprompted; checked 287,040 ÷ 138.
A10: S02 | B10: =IF(A10="","",IFERROR(INDEX(Sessions!$C$5:$C$16,MATCH(A10,Sessions!$A$5:$A$16,0))&" "&INDEX(Sessions!$D$5:$D$16,MATCH(A10,Sessions!$A$5:$A$16,0)),"")) -> P3 Dr. Rainer Hollmann | C10: T4 | D10: =IF(C10="","",IFERROR(INDEX(Lists!$C$5:$C$9,MATCH(C10,Lists!$A$5:$A$9,0)),"")) -> S3 | E10: Success | F10: 30 | G10: 6 | H10: N | I10: Recalled the saving and the 93% after 10 seconds.
A11: S02 | B11: =IF(A11="","",IFERROR(INDEX(Sessions!$C$5:$C$16,MATCH(A11,Sessions!$A$5:$A$16,0))&" "&INDEX(Sessions!$D$5:$D$16,MATCH(A11,Sessions!$A$5:$A$16,0)),"")) -> P3 Dr. Rainer Hollmann | C11: T5 | D11: =IF(C11="","",IFERROR(INDEX(Lists!$C$5:$C$9,MATCH(C11,Lists!$A$5:$A$9,0)),"")) -> S2 | E11: Success | F11: 55 | G11: 5 | H11: N | I11: Asked whether the 2027 forecast assumes the same discount.
A12: S03 | B12: =IF(A12="","",IFERROR(INDEX(Sessions!$C$5:$C$16,MATCH(A12,Sessions!$A$5:$A$16,0))&" "&INDEX(Sessions!$D$5:$D$16,MATCH(A12,Sessions!$A$5:$A$16,0)),"")) -> P4 Prof. Dr. Sabine Aigner | C12: T4 | D12: =IF(C12="","",IFERROR(INDEX(Lists!$C$5:$C$9,MATCH(C12,Lists!$A$5:$A$9,0)),"")) -> S3 | E12: Success | F12: 25 | G12: 5 | H12: N | I12: Remembered the People tile first: "Our researchers edit for them – that matters to me."
A13: S03 | B13: =IF(A13="","",IFERROR(INDEX(Sessions!$C$5:$C$16,MATCH(A13,Sessions!$A$5:$A$16,0))&" "&INDEX(Sessions!$D$5:$D$16,MATCH(A13,Sessions!$A$5:$A$16,0)),"")) -> P4 Prof. Dr. Sabine Aigner | C13: T2 | D13: =IF(C13="","",IFERROR(INDEX(Lists!$C$5:$C$9,MATCH(C13,Lists!$A$5:$A$9,0)),"")) -> S2 → S4 | E13: With help | F13: 140 | G13: 3 | H13: Y | I13: "Who checked this besides Lumen?" Wanted an independent source.
A14: S04 | B14: =IF(A14="","",IFERROR(INDEX(Sessions!$C$5:$C$16,MATCH(A14,Sessions!$A$5:$A$16,0))&" "&INDEX(Sessions!$D$5:$D$16,MATCH(A14,Sessions!$A$5:$A$16,0)),"")) -> P6 Dr. Ana Ferreira | C14: T1 | D14: =IF(C14="","",IFERROR(INDEX(Lists!$C$5:$C$9,MATCH(C14,Lists!$A$5:$A$9,0)),"")) -> S1 → S2 | E14: Success | F14: 50 | G14: 6 | H14: N | I14: Would have taken it for marketing if not addressed to the library.
A15: S04 | B15: =IF(A15="","",IFERROR(INDEX(Sessions!$C$5:$C$16,MATCH(A15,Sessions!$A$5:$A$16,0))&" "&INDEX(Sessions!$D$5:$D$16,MATCH(A15,Sessions!$A$5:$A$16,0)),"")) -> P6 Dr. Ana Ferreira | C15: T4 | D15: =IF(C15="","",IFERROR(INDEX(Lists!$C$5:$C$9,MATCH(C15,Lists!$A$5:$A$9,0)),"")) -> S3 | E15: Success | F15: 35 | G15: 6 | H15: N | I15: Pleased to be named; asked whether she agreed to it.
A16: S05 | B16: =IF(A16="","",IFERROR(INDEX(Sessions!$C$5:$C$16,MATCH(A16,Sessions!$A$5:$A$16,0))&" "&INDEX(Sessions!$D$5:$D$16,MATCH(A16,Sessions!$A$5:$A$16,0)),"")) -> P2 Jonas Brändli | C16: T1 | D16: =IF(C16="","",IFERROR(INDEX(Lists!$C$5:$C$9,MATCH(C16,Lists!$A$5:$A$9,0)),"")) -> S1 → S2 | E16: Success | F16: 40 | G16: 6 | H16: N | I16: Liked that no login is needed.
... A20: S06 | B20: =IF(A20="","",IFERROR(INDEX(Sessions!$C$5:$C$16,MATCH(A20,Sessions!$A$5:$A$16,0))&" "&INDEX(Sessions!$D$5:$D$16,MATCH(A20,Sessions!$A$5:$A$16,0)),"")) -> P5 Ulrike Sandmann | C20: T4 | D20: =IF(C20="","",IFERROR(INDEX(Lists!$C$5:$C$9,MATCH(C20,Lists!$A$5:$A$9,0)),"")) -> S3 | E20: With help | F20: 60 | G20: 4 | H20: Y | I20: "Without a peer comparison I can't use this with my members."
B21: =IF(A21="","",IFERROR(INDEX(Sessions!$C$5:$C$16,MATCH(A21,Sessions!$A$5:$A$16,0))&" "&INDEX(Sessions!$D$5:$D$16,MATCH(A21,Sessions!$A$5:$A$16,0)),"")) | D21: =IF(C21="","",IFERROR(INDEX(Lists!$C$5:$C$9,MATCH(C21,Lists!$A$5:$A$9,0)),""))
B22: =IF(A22="","",IFERROR(INDEX(Sessions!$C$5:$C$16,MATCH(A22,Sessions!$A$5:$A$16,0))&" "&INDEX(Sessions!$D$5:$D$16,MATCH(A22,Sessions!$A$5:$A$16,0)),"")) | D22: =IF(C22="","",IFERROR(INDEX(Lists!$C$5:$C$9,MATCH(C22,Lists!$A$5:$A$9,0)),""))
B23: =IF(A23="","",IFERROR(INDEX(Sessions!$C$5:$C$16,MATCH(A23,Sessions!$A$5:$A$16,0))&" "&INDEX(Sessions!$D$5:$D$16,MATCH(A23,Sessions!$A$5:$A$16,0)),"")) | D23: =IF(C23="","",IFERROR(INDEX(Lists!$C$5:$C$9,MATCH(C23,Lists!$A$5:$A$9,0)),""))
B24: =IF(A24="","",IFERROR(INDEX(Sessions!$C$5:$C$16,MATCH(A24,Sessions!$A$5:$A$16,0))&" "&INDEX(Sessions!$D$5:$D$16,MATCH(A24,Sessions!$A$5:$A$16,0)),"")) | D24: =IF(C24="","",IFERROR(INDEX(Lists!$C$5:$C$9,MATCH(C24,Lists!$A$5:$A$9,0)),""))
B25: =IF(A25="","",IFERROR(INDEX(Sessions!$C$5:$C$16,MATCH(A25,Sessions!$A$5:$A$16,0))&" "&INDEX(Sessions!$D$5:$D$16,MATCH(A25,Sessions!$A$5:$A$16,0)),"")) | D25: =IF(C25="","",IFERROR(INDEX(Lists!$C$5:$C$9,MATCH(C25,Lists!$A$5:$A$9,0)),""))
B26: =IF(A26="","",IFERROR(INDEX(Sessions!$C$5:$C$16,MATCH(A26,Sessions!$A$5:$A$16,0))&" "&INDEX(Sessions!$D$5:$D$16,MATCH(A26,Sessions!$A$5:$A$16,0)),"")) | D26: =IF(C26="","",IFERROR(INDEX(Lists!$C$5:$C$9,MATCH(C26,Lists!$A$5:$A$9,0)),""))
B27: =IF(A27="","",IFERROR(INDEX(Sessions!$C$5:$C$16,MATCH(A27,Sessions!$A$5:$A$16,0))&" "&INDEX(Sessions!$D$5:$D$16,MATCH(A27,Sessions!$A$5:$A$16,0)),"")) | D27: =IF(C27="","",IFERROR(INDEX(Lists!$C$5:$C$9,MATCH(C27,Lists!$A$5:$A$9,0)),""))
B28: =IF(A28="","",IFERROR(INDEX(Sessions!$C$5:$C$16,MATCH(A28,Sessions!$A$5:$A$16,0))&" "&INDEX(Sessions!$D$5:$D$16,MATCH(A28,Sessions!$A$5:$A$16,0)),"")) | D28: =IF(C28="","",IFERROR(INDEX(Lists!$C$5:$C$9,MATCH(C28,Lists!$A$5:$A$9,0)),""))
B29: =IF(A29="","",IFERROR(INDEX(Sessions!$C$5:$C$16,MATCH(A29,Sessions!$A$5:$A$16,0))&" "&INDEX(Sessions!$D$5:$D$16,MATCH(A29,Sessions!$A$5:$A$16,0)),"")) | D29: =IF(C29="","",IFERROR(INDEX(Lists!$C$5:$C$9,MATCH(C29,Lists!$A$5:$A$9,0)),""))
B30: =IF(A30="","",IFERROR(INDEX(Sessions!$C$5:$C$16,MATCH(A30,Sessions!$A$5:$A$16,0))&" "&INDEX(Sessions!$D$5:$D$16,MATCH(A30,Sessions!$A$5:$A$16,0)),"")) | D30: =IF(C30="","",IFERROR(INDEX(Lists!$C$5:$C$9,MATCH(C30,Lists!$A$5:$A$9,0)),""))
B31: =IF(A31="","",IFERROR(INDEX(Sessions!$C$5:$C$16,MATCH(A31,Sessions!$A$5:$A$16,0))&" "&INDEX(Sessions!$D$5:$D$16,MATCH(A31,Sessions!$A$5:$A$16,0)),"")) | D31: =IF(C31="","",IFERROR(INDEX(Lists!$C$5:$C$9,MATCH(C31,Lists!$A$5:$A$9,0)),""))
B32: =IF(A32="","",IFERROR(INDEX(Sessions!$C$5:$C$16,MATCH(A32,Sessions!$A$5:$A$16,0))&" "&INDEX(Sessions!$D$5:$D$16,MATCH(A32,Sessions!$A$5:$A$16,0)),"")) | D32: =IF(C32="","",IFERROR(INDEX(Lists!$C$5:$C$9,MATCH(C32,Lists!$A$5:$A$9,0)),""))
... B64: =IF(A64="","",IFERROR(INDEX(Sessions!$C$5:$C$16,MATCH(A64,Sessions!$A$5:$A$16,0))&" "&INDEX(Sessions!$D$5:$D$16,MATCH(A64,Sessions!$A$5:$A$16,0)),"")) | D64: =IF(C64="","",IFERROR(INDEX(Lists!$C$5:$C$9,MATCH(C64,Lists!$A$5:$A$9,0)),""))

Sheet Observations
A1: Observations
A2: One row per session: the assumption fields and debrief ratings. Use NA where a task was not run.
A4: Session | B4: Persona | C4: A1 Forward unchanged (Y/N) | D4: A2 Acted on email unprompted (Y/N/NA) | E4: A3 Trust (1–5) | F4: Found method unprompted (Y/N/NA) | G4: A4 Most persuasive tile | H4: A5 Must-have missing (Y/N) | I4: Missing items | J4: A6 Expansion interest (Y/N/NA) | K4: Budget intent (1–5) | L4: Usefulness (1–5) | M4: Email over login (1–5) | N4: Forward intent (1–5) | O4: Closing quote
A5: S01 | B5: =IF(A5="","",IFERROR(INDEX(Sessions!$C$5:$C$16,MATCH(A5,Sessions!$A$5:$A$16,0))&" "&INDEX(Sessions!$D$5:$D$16,MATCH(A5,Sessions!$A$5:$A$16,0)),"")) -> P1 Dr. Miriam Kessler | C5: N | D5: Y | E5: 5 | F5: Y | G5: Compliance | H5: Y | I5: Board meeting date ([YOUR DATE] placeholder) | J5: Y | K5: 4 | L5: 5 | M5: 5 | N5: 4 | O5: "This saves me two days – if I can add the meeting date."
A6: S02 | B6: =IF(A6="","",IFERROR(INDEX(Sessions!$C$5:$C$16,MATCH(A6,Sessions!$A$5:$A$16,0))&" "&INDEX(Sessions!$D$5:$D$16,MATCH(A6,Sessions!$A$5:$A$16,0)),"")) -> P3 Dr. Rainer Hollmann | C6: Y | D6: NA | E6: 4 | F6: Y | G6: Cost | H6: Y | I6: Comparison with other publishers | J6: Y | K6: 4 | L6: 4 | M6: 4 | N6: 5 | O6: "One page is right. I'd still want to know how other publishers compare."
A7: S03 | B7: =IF(A7="","",IFERROR(INDEX(Sessions!$C$5:$C$16,MATCH(A7,Sessions!$A$5:$A$16,0))&" "&INDEX(Sessions!$D$5:$D$16,MATCH(A7,Sessions!$A$5:$A$16,0)),"")) -> P4 Prof. Dr. Sabine Aigner | C7: Y | D7: NA | E7: 3 | F7: N | G7: People | H7: N | J7: N | K7: 2 | L7: 3 | M7: 3 | N7: 4 | O7: "I'd sign this – but I'd ask who checked the numbers."
A8: S04 | B8: =IF(A8="","",IFERROR(INDEX(Sessions!$C$5:$C$16,MATCH(A8,Sessions!$A$5:$A$16,0))&" "&INDEX(Sessions!$D$5:$D$16,MATCH(A8,Sessions!$A$5:$A$16,0)),"")) -> P6 Dr. Ana Ferreira | C8: Y | D8: N | E8: 4 | F8: NA | G8: People | H8: N | J8: NA | L8: 5 | M8: 4 | N8: 5 | O8: "Seeing my editing work on a board slide is a first."
A9: S05 | B9: =IF(A9="","",IFERROR(INDEX(Sessions!$C$5:$C$16,MATCH(A9,Sessions!$A$5:$A$16,0))&" "&INDEX(Sessions!$D$5:$D$16,MATCH(A9,Sessions!$A$5:$A$16,0)),"")) -> P2 Jonas Brändli | C9: Y | D9: Y | E9: 4 | F9: Y | G9: Compliance | H9: Y | I9: SNSF compliance in the funder figure | J9: N | K9: 2 | L9: 4 | M9: 5 | N9: 4 | O9: "Without SNSF I'd still have to build my own table."
A10: S06 | B10: =IF(A10="","",IFERROR(INDEX(Sessions!$C$5:$C$16,MATCH(A10,Sessions!$A$5:$A$16,0))&" "&INDEX(Sessions!$D$5:$D$16,MATCH(A10,Sessions!$A$5:$A$16,0)),"")) -> P5 Ulrike Sandmann | C10: N | D10: NA | E10: 3 | F10: Y | G10: Cost | H10: Y | I10: Peer benchmark, standard monitoring fields | J10: N | K10: 3 | L10: 3 | M10: 4 | N10: 2 | O10: "Good for one university. For 14 I need the same figures from every publisher."
A11: S07 | B11: =IF(A11="","",IFERROR(INDEX(Sessions!$C$5:$C$16,MATCH(A11,Sessions!$A$5:$A$16,0))&" "&INDEX(Sessions!$D$5:$D$16,MATCH(A11,Sessions!$A$5:$A$16,0)),"")) -> R1 [real librarian 1]
A12: S08 | B12: =IF(A12="","",IFERROR(INDEX(Sessions!$C$5:$C$16,MATCH(A12,Sessions!$A$5:$A$16,0))&" "&INDEX(Sessions!$D$5:$D$16,MATCH(A12,Sessions!$A$5:$A$16,0)),"")) -> R2 [real librarian 2]
A13: S09 | B13: =IF(A13="","",IFERROR(INDEX(Sessions!$C$5:$C$16,MATCH(A13,Sessions!$A$5:$A$16,0))&" "&INDEX(Sessions!$D$5:$D$16,MATCH(A13,Sessions!$A$5:$A$16,0)),"")) -> R3 [real director]
A14: S10 | B14: =IF(A14="","",IFERROR(INDEX(Sessions!$C$5:$C$16,MATCH(A14,Sessions!$A$5:$A$16,0))&" "&INDEX(Sessions!$D$5:$D$16,MATCH(A14,Sessions!$A$5:$A$16,0)),""))
A15: S11 | B15: =IF(A15="","",IFERROR(INDEX(Sessions!$C$5:$C$16,MATCH(A15,Sessions!$A$5:$A$16,0))&" "&INDEX(Sessions!$D$5:$D$16,MATCH(A15,Sessions!$A$5:$A$16,0)),""))
A16: S12 | B16: =IF(A16="","",IFERROR(INDEX(Sessions!$C$5:$C$16,MATCH(A16,Sessions!$A$5:$A$16,0))&" "&INDEX(Sessions!$D$5:$D$16,MATCH(A16,Sessions!$A$5:$A$16,0)),""))

Sheet Lists
A1: Lists
A2: Reference values for the dropdowns and lookups. Change only if the test guide changes.
A4: Task | B4: Name | C4: Screens | D4: Assumptions | F4: Result | G4: Yes/No | H4: Yes/No/NA | I4: Tile | J4: Mode | K4: Status
A5: T1 | B5: Receive the kit | C5: S1 → S2 | D5: A2, A4 | F5: Success | G5: Y | H5: Y | I5: Cost | J5: Twin | K5: Planned
A6: T2 | B6: Check a figure | C6: S2 → S4 | D6: A3 | F6: With help | G6: N | H6: N | I6: Compliance | J6: Real | K6: Done
A7: T3 | B7: Pass it on | C7: S3 → S5 | D7: A1, A5 | F7: Failed | H7: NA | I7: People | K7: Cancelled
A8: T4 | B8: Make the case | C8: S3 | D8: A4
A9: T5 | B9: Plan ahead | C9: S2 | D9: A6
